cocotbext/interfaces/__init__.py
cocotbext/interfaces/model.py
cocotbext/interfaces/signal.py
cocotbext/interfaces/avalon/__init__.py
cocotbext/interfaces/avalon/driver.py
cocotbext/interfaces/avalon/monitor.py
cocotbext/interfaces/avalon/streaming.py
cocotbext_interfaces-0.1.1.dist-info/LICENSE
cocotbext_interfaces-0.1.1.dist-info/METADATA
cocotbext_interfaces-0.1.1.dist-info/WHEEL
cocotbext_interfaces-0.1.1.dist-info/top_level.txt
cocotbext_interfaces-0.1.1.dist-info/RECORD
