Metadata-Version: 2.1
Name: cocotbext-interfaces
Version: 0.1.1
Summary: UNKNOWN
Home-page: UNKNOWN
Author: Nicholas Redd
Author-email: redd@google.com
License: UNKNOWN
Platform: UNKNOWN
Classifier: Programming Language :: Python :: 3
Classifier: Operating System :: OS Independent
Classifier: Topic :: Scientific/Engineering :: Electronic Design Automation (EDA)
Requires-Python: >=3.6
Requires-Dist: cocotb
Requires-Dist: transitions
